src/__init__.py
src/config.py
src/constants.py
src/factory.py
src/main.py
src/analyzers/__init__.py
src/analyzers/base_analyzer.py
src/analyzers/benignware_analyzer.py
src/analyzers/malware_analyzer.py
src/utils/__init__.py
src/utils/elf_utils.py
src/utils/hash_utils.py
src/utils/packer_utils.py
pyelflabeler-0.3.2.dist-info/METADATA
pyelflabeler-0.3.2.dist-info/WHEEL
pyelflabeler-0.3.2.dist-info/entry_points.txt
pyelflabeler-0.3.2.dist-info/RECORD
