Metadata-Version: 2.4
Name: pyelflabeler
Version: 0.3.2
Summary: ELF Binary Analysis Tool - Label malware or benignware datasets
Project-URL: Homepage, https://github.com/bolin8017/pyelflabeler
Project-URL: Repository, https://github.com/bolin8017/pyelflabeler
Project-URL: Issues, https://github.com/bolin8017/pyelflabeler/issues
Author-email: bolin8017 <bolin8017@gmail.com>
License: MIT
Keywords: binary-analysis,dataset,elf,labeling,malware,security
Classifier: Development Status :: 4 - Beta
Classifier: Intended Audience :: Developers
Classifier: Intended Audience :: Science/Research
Classifier: License :: OSI Approved :: MIT License
Classifier: Programming Language :: Python :: 3
Classifier: Programming Language :: Python :: 3.10
Classifier: Programming Language :: Python :: 3.11
Classifier: Programming Language :: Python :: 3.12
Classifier: Topic :: Security
Classifier: Topic :: Software Development :: Libraries :: Python Modules
Requires-Python: >=3.10
Requires-Dist: avclass-malicialab>=2.8.10
Requires-Dist: pyelftools>=0.29
Requires-Dist: tqdm>=4.65.0
Provides-Extra: dev
Requires-Dist: pytest-cov>=4.0.0; extra == 'dev'
Requires-Dist: pytest>=7.0.0; extra == 'dev'
